README.md
setup.py
veba/__init__.py
veba/veba.py
veba.egg-info/PKG-INFO
veba.egg-info/SOURCES.txt
veba.egg-info/dependency_links.txt
veba.egg-info/top_level.txt