Metadata-Version: 1.0
Name: veba
Version: 2021.8.3a0
Summary: Virus Eukaryote Bacteria Archaea
Home-page: UNKNOWN
Author: Josh L. Espinoza
Author-email: jespinoz@jcvi.org
License: BSD-3
Platform: UNKNOWN
